GridSearchHelper/__init__.py
GridSearchHelper/grid_search.py
GridSearchHelper/models.py
GridSearchHelper-0.8.0.dist-info/LICENCE.txt
GridSearchHelper-0.8.0.dist-info/METADATA
GridSearchHelper-0.8.0.dist-info/WHEEL
GridSearchHelper-0.8.0.dist-info/top_level.txt
GridSearchHelper-0.8.0.dist-info/RECORD
