Metadata-Version: 2.1
Name: GridSearchHelper
Version: 0.8.0
Summary: Advanced hyperparameter tuning using grid search for ML models
Home-page: https://github.com/alimovabdulla/GridSearchHelper
Author: Abdulla Alimov
Author-email: abdullaalimov555@gmail.com
License: MIT
Project-URL: Bug Tracker, https://github.com/alimovabdulla/GridSearchHelper/
Project-URL: Documentation, https://github.com/alimovabdulla/GridSearchHelper/
Keywords: machine-learning grid-search hyperparameter-tuning scikit-learn
Platform: UNKNOWN
Classifier: Programming Language :: Python :: 3
Classifier: License :: OSI Approved :: MIT License
Classifier: Operating System :: OS Independent
Classifier: Intended Audience :: Developers
Classifier: Intended Audience :: Science/Research
Classifier: Topic :: Scientific/Engineering :: Artificial Intelligence
Requires-Python: >=3.6
License-File: LICENCE.txt
Requires-Dist: scikit-learn>=0.24.0
Requires-Dist: numpy>=1.19.0
